agpypeline/__init__.py
agpypeline/algorithm.py
agpypeline/checkmd.py
agpypeline/configuration.py
agpypeline/entrypoint.py
agpypeline/environment.py
agpypeline/geoimage.py
agpypeline/geometries.py
agpypeline/lasfile.py
integration_tests/__init__.py
integration_tests/basic_algorithm.py
integration_tests/test_integration.py
agpypeline-0.0.52.dist-info/LICENSE
agpypeline-0.0.52.dist-info/METADATA
agpypeline-0.0.52.dist-info/WHEEL
agpypeline-0.0.52.dist-info/top_level.txt
agpypeline-0.0.52.dist-info/RECORD
