Metadata-Version: 2.1
Name: agpypeline
Version: 0.0.52
Summary: Installable package for entrypoint and drone-specific environment code within a transformer
Home-page: https://github.com/AgPipeline/agpypeline
Author: Jacob van der Leeuw
Author-email: jvanderleeuw@email.arizona.edu
Classifier: Programming Language :: Python :: 3
Classifier: License :: OSI Approved :: BSD License
Classifier: Operating System :: OS Independent
Requires-Python: >=3.8
License-File: LICENSE
Requires-Dist: setuptools (==65.5.1)
Requires-Dist: numpy
Requires-Dist: influxdb
Requires-Dist: requests (>=2.21.0)
Requires-Dist: python-dateutil
Requires-Dist: utm
Requires-Dist: matplotlib
Requires-Dist: Pillow
Requires-Dist: scipy
Requires-Dist: piexif
Requires-Dist: cryptography
Requires-Dist: pyyaml
Requires-Dist: pygdal (==3.4.1.*)
